ShikongZhiwai/Dockerfile
ShikongZhiwai/README.md
ShikongZhiwai/__init__.py
ShikongZhiwai/__main__.py
ShikongZhiwai/file.epub
ShikongZhiwai/index.html
ShikongZhiwai/css/__init__.py
ShikongZhiwai/css/annotations.css
ShikongZhiwai/css/main.css
ShikongZhiwai/css/normalize.css
ShikongZhiwai/css/popup.css
ShikongZhiwai/font/__init__.py
ShikongZhiwai/font/fontello.eot
ShikongZhiwai/font/fontello.svg
ShikongZhiwai/font/fontello.ttf
ShikongZhiwai/font/fontello.woff
ShikongZhiwai/img/__init__.py
ShikongZhiwai/img/annotator-glyph-sprite.png
ShikongZhiwai/img/annotator-icon-sprite.png
ShikongZhiwai/img/apple-touch-icon.png
ShikongZhiwai/img/cancelfullscreen.png
ShikongZhiwai/img/close.png
ShikongZhiwai/img/fullscreen.png
ShikongZhiwai/img/loader.gif
ShikongZhiwai/img/menu-icon.png
ShikongZhiwai/img/save.png
ShikongZhiwai/img/saved.png
ShikongZhiwai/img/settings-s.png
ShikongZhiwai/img/settings.png
ShikongZhiwai/img/star.png
ShikongZhiwai/js/__init__.py
ShikongZhiwai/js/epub.js
ShikongZhiwai/js/epub.min.js
ShikongZhiwai/js/epub.min.map
ShikongZhiwai/js/hooks.min.js
ShikongZhiwai/js/hooks.min.map
ShikongZhiwai/js/reader.js
ShikongZhiwai/js/reader.js.map
ShikongZhiwai/js/reader.min.js
ShikongZhiwai/js/reader.min.map
ShikongZhiwai/js/hooks/__init__.py
ShikongZhiwai/js/hooks/extensions/__init__.py
ShikongZhiwai/js/hooks/extensions/highlight.js
ShikongZhiwai/js/libs/__init__.py
ShikongZhiwai/js/libs/jquery.min.js
ShikongZhiwai/js/libs/localforage.min.js
ShikongZhiwai/js/libs/screenfull.js
ShikongZhiwai/js/libs/screenfull.min.js
ShikongZhiwai/js/libs/zip.min.js
ShikongZhiwai/js/plugins/__init__.py
ShikongZhiwai/js/plugins/hypothesis.js
ShikongZhiwai/js/plugins/search.js
shikong_zhiwai-2022.10.9.1.dist-info/METADATA
shikong_zhiwai-2022.10.9.1.dist-info/WHEEL
shikong_zhiwai-2022.10.9.1.dist-info/entry_points.txt
shikong_zhiwai-2022.10.9.1.dist-info/top_level.txt
shikong_zhiwai-2022.10.9.1.dist-info/RECORD
